pymodbus_3p3v/__init__.py
pymodbus_3p3v/constants.py
pymodbus_3p3v/device.py
pymodbus_3p3v/events.py
pymodbus_3p3v/exceptions.py
pymodbus_3p3v/logging.py
pymodbus_3p3v/payload.py
pymodbus_3p3v/py.typed
pymodbus_3p3v/transaction.py
pymodbus_3p3v/utilities.py
pymodbus_3p3v/client/__init__.py
pymodbus_3p3v/client/base.py
pymodbus_3p3v/client/mixin.py
pymodbus_3p3v/client/modbusclientprotocol.py
pymodbus_3p3v/client/serial.py
pymodbus_3p3v/client/tcp.py
pymodbus_3p3v/client/tls.py
pymodbus_3p3v/client/udp.py
pymodbus_3p3v/datastore/__init__.py
pymodbus_3p3v/datastore/context.py
pymodbus_3p3v/datastore/remote.py
pymodbus_3p3v/datastore/simulator.py
pymodbus_3p3v/datastore/store.py
pymodbus_3p3v/framer/__init__.py
pymodbus_3p3v/framer/ascii.py
pymodbus_3p3v/framer/base.py
pymodbus_3p3v/framer/rtu.py
pymodbus_3p3v/framer/socket.py
pymodbus_3p3v/framer/tls.py
pymodbus_3p3v/pdu/__init__.py
pymodbus_3p3v/pdu/bit_read_message.py
pymodbus_3p3v/pdu/bit_write_message.py
pymodbus_3p3v/pdu/decoders.py
pymodbus_3p3v/pdu/diag_message.py
pymodbus_3p3v/pdu/file_message.py
pymodbus_3p3v/pdu/mei_message.py
pymodbus_3p3v/pdu/other_message.py
pymodbus_3p3v/pdu/pdu.py
pymodbus_3p3v/pdu/register_read_message.py
pymodbus_3p3v/pdu/register_write_message.py
pymodbus_3p3v/server/__init__.py
pymodbus_3p3v/server/async_io.py
pymodbus_3p3v/server/simulator/__init__.py
pymodbus_3p3v/server/simulator/custom_actions.py
pymodbus_3p3v/server/simulator/http_server.py
pymodbus_3p3v/server/simulator/main.py
pymodbus_3p3v/transport/__init__.py
pymodbus_3p3v/transport/serialtransport.py
pymodbus_3p3v/transport/transport.py
pymodbus_3p3v-3.7.4.5.dist-info/AUTHORS.rst
pymodbus_3p3v-3.7.4.5.dist-info/LICENSE
pymodbus_3p3v-3.7.4.5.dist-info/METADATA
pymodbus_3p3v-3.7.4.5.dist-info/WHEEL
pymodbus_3p3v-3.7.4.5.dist-info/entry_points.txt
pymodbus_3p3v-3.7.4.5.dist-info/top_level.txt
pymodbus_3p3v-3.7.4.5.dist-info/zip-safe
pymodbus_3p3v-3.7.4.5.dist-info/RECORD
