Metadata-Version: 2.1
Name: pymodbus_3p3v
Version: 3.7.4.5
Summary: A fully featured modbus protocol stack in python. Fixed serial not showing error. Changed API to output server exit reason.
Author: Galen Collins, Jan Iversen
License: BSD-3-Clause
Project-URL: Homepage, https://github.com/3p3v/pymodbus/
Project-URL: Source Code, https://github.com/3p3v/pymodbus
Keywords: modbus,asyncio,scada,client,server,simulator
Platform: 'Linux'
Platform: 'Mac OS X'
Platform: 'Win'
Classifier: Development Status :: 5 - Production/Stable
Classifier: Environment :: Console
Classifier: Framework :: AsyncIO
Classifier: Intended Audience :: Developers
Classifier: License :: OSI Approved :: BSD License
Classifier: Operating System :: POSIX :: Linux
Classifier: Operating System :: Unix
Classifier: Operating System :: MacOS :: MacOS X
Classifier: Operating System :: OS Independent
Classifier: Operating System :: Microsoft
Classifier: Programming Language :: Python :: 3.9
Classifier: Programming Language :: Python :: 3.10
Classifier: Programming Language :: Python :: 3.11
Classifier: Programming Language :: Python :: 3.12
Classifier: Programming Language :: Python :: 3.13
Classifier: Topic :: System :: Networking
Classifier: Topic :: Utilities
Requires-Python: >=3.9.0
License-File: LICENSE
License-File: AUTHORS.rst
Provides-Extra: all
Requires-Dist: pymodbus[development,documentation,repl,serial,simulator] ; extra == 'all'
Provides-Extra: development
Requires-Dist: build >=1.2.2 ; extra == 'development'
Requires-Dist: codespell >=2.3.0 ; extra == 'development'
Requires-Dist: coverage >=7.6.1 ; extra == 'development'
Requires-Dist: mypy >=1.11.2 ; extra == 'development'
Requires-Dist: pylint >=3.3.0 ; extra == 'development'
Requires-Dist: pytest >=8.3.3 ; extra == 'development'
Requires-Dist: pytest-asyncio >=0.24.0 ; extra == 'development'
Requires-Dist: pytest-cov >=5.0.0 ; extra == 'development'
Requires-Dist: pytest-timeout >=2.3.1 ; extra == 'development'
Requires-Dist: pytest-xdist >=3.6.1 ; extra == 'development'
Requires-Dist: pytest-aiohttp >=1.0.5 ; extra == 'development'
Requires-Dist: ruff >=0.5.3 ; extra == 'development'
Requires-Dist: twine >=5.1.1 ; extra == 'development'
Requires-Dist: types-Pygments ; extra == 'development'
Requires-Dist: types-pyserial ; extra == 'development'
Requires-Dist: pytest-profiling >=1.7.0 ; (python_version < "3.13") and extra == 'development'
Provides-Extra: documentation
Requires-Dist: recommonmark >=0.7.1 ; extra == 'documentation'
Requires-Dist: Sphinx >=7.3.7 ; extra == 'documentation'
Requires-Dist: sphinx-rtd-theme >=2.0.0 ; extra == 'documentation'
Provides-Extra: repl
Requires-Dist: pymodbus-repl >=2.0.4 ; extra == 'repl'
Provides-Extra: serial
Requires-Dist: pyserial >=3.5 ; extra == 'serial'
Provides-Extra: simulator
Requires-Dist: aiohttp >=3.8.6 ; (python_version < "3.12") and extra == 'simulator'
Requires-Dist: aiohttp >=3.10.5 ; (python_version >= "3.12") and extra == 'simulator'
